eightest/__init__.py
eightest/decorators.py
eightest/exceptions.py
eightest/logger.py
eightest/manage.py
eightest/process.py
eightest/runner.py
eightest/searcher.py
eightest/testcase.py
eightest/utilities.py
eightest/gui/__init__.py
eightest/gui/asgi.py
eightest/gui/settings.py
eightest/gui/urls.py
eightest/gui/wsgi.py
eightest/gui/apps/home/__init__.py
eightest/gui/apps/home/admin.py
eightest/gui/apps/home/apps.py
eightest/gui/apps/home/models.py
eightest/gui/apps/home/tests.py
eightest/gui/apps/home/urls.py
eightest/gui/apps/home/views.py
eightest/gui/apps/home/migrations/__init__.py
eightest/gui/apps/navbar/__init__.py
eightest/gui/apps/navbar/admin.py
eightest/gui/apps/navbar/apps.py
eightest/gui/apps/navbar/models.py
eightest/gui/apps/navbar/tests.py
eightest/gui/apps/navbar/urls.py
eightest/gui/apps/navbar/views.py
eightest/gui/apps/navbar/migrations/__init__.py
eightest/gui/static/images/eightest-logo.png
eightest/gui/static/images/favicon.ico
eightest/gui/static/styles/footer.sass
eightest/gui/static/styles/home.sass
eightest/gui/static/styles/navbar.sass
eightest/gui/static/styles/style.sass
eightest/gui/templates/footer.html
eightest/gui/templates/home.html
eightest/gui/templates/main.html
eightest/gui/templates/navbar.html
eightest-0.5.0.dist-info/METADATA
eightest-0.5.0.dist-info/WHEEL
eightest-0.5.0.dist-info/licenses/LICENSE
eightest-0.5.0.dist-info/RECORD
