Metadata-Version: 2.1
Name: eightest
Version: 0.5.0
Summary: GUI equipped Test Framework
Project-URL: Homepage, https://github.com/Alraku/eightest
Project-URL: Bug Tracker, https://github.com/Alraku/eightest/issues
Author-email: "Alraku (Krzysztof Rakowski)" <ekoalraku@gmail.com>
License-File: LICENSE
Classifier: Development Status :: 2 - Pre-Alpha
Classifier: Framework :: Django :: 4.1
Classifier: Intended Audience :: Developers
Classifier: License :: OSI Approved :: MIT License
Classifier: Operating System :: MacOS :: MacOS X
Classifier: Operating System :: Microsoft :: Windows
Classifier: Operating System :: OS Independent
Classifier: Operating System :: Unix
Classifier: Programming Language :: Python :: 3
Requires-Python: >=3.10
